fastjsondiff/__init__.py
fastjsondiff/_core.py
fastjsondiff/libfastjsondiff_core.dylib
fastjsondiff/models.py
fastjsondiff_zig-26.1.dist-info/licenses/LICENSE
fastjsondiff_zig-26.1.dist-info/METADATA
fastjsondiff_zig-26.1.dist-info/WHEEL
fastjsondiff_zig-26.1.dist-info/top_level.txt
fastjsondiff_zig-26.1.dist-info/RECORD
