Metadata-Version: 2.4
Name: fastjsondiff-zig
Version: 26.1
Summary: High-performance JSON comparison library with Zig-powered core
Author-email: Adylzhan Khashtamov <adil.khashtamov@gmail.com>
License-Expression: MIT
Project-URL: Homepage, https://github.com/adylzhan/fastjsondiff
Project-URL: Documentation, https://github.com/adylzhan/fastjsondiff#readme
Project-URL: Repository, https://github.com/adylzhan/fastjsondiff.git
Project-URL: Issues, https://github.com/adylzhan/fastjsondiff/issues
Keywords: json,diff,compare,performance,zig
Classifier: Development Status :: 3 - Alpha
Classifier: Intended Audience :: Developers
Classifier: Programming Language :: Python :: 3
Classifier: Programming Language :: Python :: 3.11
Classifier: Programming Language :: Python :: 3.12
Classifier: Programming Language :: Python :: 3.13
Classifier: Programming Language :: Python :: 3.14
Classifier: Topic :: Software Development :: Libraries :: Python Modules
Classifier: Topic :: Text Processing :: General
Requires-Python: >=3.11
License-File: LICENSE
Provides-Extra: dev
Requires-Dist: pytest>=7.2.2; extra == "dev"
Requires-Dist: pytest-benchmark>=4.0.0; extra == "dev"
Provides-Extra: test
Requires-Dist: pytest>=7.2.2; extra == "test"
Requires-Dist: pytest-benchmark>=4.0.0; extra == "test"
Dynamic: license-file
